{"cameraMode":{"drawMode":0,"name":"Shaded","section":"Shading Mode"},"sceneLighting":true,"audioPlay":false,"sceneViewState":{"showFog":true,"showMaterialUpdate":false,"showSkybox":true,"showFlares":true,"showImageEffects":true,"showParticleSystems":true},"in2DMode":false,"pivot":{"x":-5.489699840545654,"y":1.4188611507415772,"z":-0.08451096713542938},"rotation":{"x":0.05040476843714714,"y":-0.6806748509407044,"z":0.0470409020781517,"w":0.7293393611907959},"size":7.296767711639404,"orthographic":false}